chaosplt_grpc/__init__.py
chaosplt_grpc/activity/__init__.py
chaosplt_grpc/activity/activity_pb2.py
chaosplt_grpc/activity/activity_pb2_grpc.py
chaosplt_grpc/activity/client.py
chaosplt_grpc/activity/message.py
chaosplt_grpc/activity/server.py
chaosplt_grpc/auth/__init__.py
chaosplt_grpc/auth/auth_pb2.py
chaosplt_grpc/auth/auth_pb2_grpc.py
chaosplt_grpc/auth/client.py
chaosplt_grpc/auth/message.py
chaosplt_grpc/auth/server.py
chaosplt_grpc/execution/__init__.py
chaosplt_grpc/execution/client.py
chaosplt_grpc/execution/execution_pb2.py
chaosplt_grpc/execution/execution_pb2_grpc.py
chaosplt_grpc/execution/message.py
chaosplt_grpc/execution/server.py
chaosplt_grpc/experiment/__init__.py
chaosplt_grpc/experiment/client.py
chaosplt_grpc/experiment/experiment_pb2.py
chaosplt_grpc/experiment/experiment_pb2_grpc.py
chaosplt_grpc/experiment/message.py
chaosplt_grpc/experiment/server.py
chaosplt_grpc/organization/__init__.py
chaosplt_grpc/organization/client.py
chaosplt_grpc/organization/message.py
chaosplt_grpc/organization/organization_pb2.py
chaosplt_grpc/organization/organization_pb2_grpc.py
chaosplt_grpc/organization/server.py
chaosplt_grpc/registration/__init__.py
chaosplt_grpc/registration/client.py
chaosplt_grpc/registration/message.py
chaosplt_grpc/registration/registration_pb2.py
chaosplt_grpc/registration/registration_pb2_grpc.py
chaosplt_grpc/registration/server.py
chaosplt_grpc/scheduler/__init__.py
chaosplt_grpc/scheduler/client.py
chaosplt_grpc/scheduler/message.py
chaosplt_grpc/scheduler/scheduler_pb2.py
chaosplt_grpc/scheduler/scheduler_pb2_grpc.py
chaosplt_grpc/scheduler/server.py
chaosplt_grpc/scheduling/__init__.py
chaosplt_grpc/scheduling/client.py
chaosplt_grpc/scheduling/message.py
chaosplt_grpc/scheduling/scheduling_pb2.py
chaosplt_grpc/scheduling/scheduling_pb2_grpc.py
chaosplt_grpc/scheduling/server.py
chaosplt_grpc/user/__init__.py
chaosplt_grpc/user/client.py
chaosplt_grpc/user/message.py
chaosplt_grpc/user/server.py
chaosplt_grpc/user/user_pb2.py
chaosplatform_grpc-0.3.0.dist-info/LICENSE
chaosplatform_grpc-0.3.0.dist-info/METADATA
chaosplatform_grpc-0.3.0.dist-info/WHEEL
chaosplatform_grpc-0.3.0.dist-info/top_level.txt
chaosplatform_grpc-0.3.0.dist-info/RECORD
