Metadata-Version: 2.1
Name: chaosplatform-grpc
Version: 0.3.0
Summary: Library of gRPC client and server for Chaos Platform services
Home-page: https://github.com/chaostoolkit/chaosplatform-grpc
Author: ChaosIQ
Author-email: contact@chaosiq.io
License: Apache Software License 2.0
Platform: UNKNOWN
Classifier: Development Status :: 4 - Beta
Classifier: Intended Audience :: Developers
Classifier: License :: OSI Approved :: Apache Software License
Classifier: Operating System :: Unix
Classifier: Operating System :: POSIX
Classifier: Programming Language :: Python
Classifier: Programming Language :: Python :: 3
Classifier: Programming Language :: Python :: 3.6
Classifier: Programming Language :: Python :: 3.7
Classifier: Programming Language :: Python :: Implementation :: CPython
Requires-Python: >=3.6.*
Requires-Dist: grpcio (==1.17.1)
Requires-Dist: simplejson (==3.15.0)
Requires-Dist: protobuf (==3.6.1)
